ibby_guess_the_number/__init__.py
ibby_guess_the_number/cli.py
ibby_guess_the_number/game.py
ibby_guess_the_number-0.1.2.dist-info/METADATA
ibby_guess_the_number-0.1.2.dist-info/WHEEL
ibby_guess_the_number-0.1.2.dist-info/entry_points.txt
ibby_guess_the_number-0.1.2.dist-info/RECORD
